README.rst
setup.py
ghostpaste/__init__.py
ghostpaste/ghostpaste.py
ghostpaste.egg-info/PKG-INFO
ghostpaste.egg-info/SOURCES.txt
ghostpaste.egg-info/dependency_links.txt
ghostpaste.egg-info/entry_points.txt
ghostpaste.egg-info/requires.txt
ghostpaste.egg-info/top_level.txt