Metadata-Version: 1.1
Name: ghostpaste
Version: 1.0.2
Summary: upload code and text to ghostbin.com
Home-page: https://github.com/kenjoe41/ghostpaste
Author: kenjoe41
Author-email: kenjoe41.nafuti@gmail.com
License: Apache Software License
Keywords: ghostbin paste ghostpaste
Platform: UNKNOWN
Classifier: Development Status :: 5 - Production/Stable
Classifier: License :: OSI Approved :: Apache Software License
